odoo/addons/tms_expense/README.rst
odoo/addons/tms_expense/__init__.py
odoo/addons/tms_expense/__manifest__.py
odoo/addons/tms_expense/data/hr_employee_driver.xml
odoo/addons/tms_expense/data/hr_expense_data.xml
odoo/addons/tms_expense/i18n/tms_expense.pot
odoo/addons/tms_expense/models/__init__.py
odoo/addons/tms_expense/models/hr_expense.py
odoo/addons/tms_expense/models/tms_driver.py
odoo/addons/tms_expense/models/tms_order.py
odoo/addons/tms_expense/readme/CONTRIBUTORS.md
odoo/addons/tms_expense/readme/CREDITS.md
odoo/addons/tms_expense/readme/DESCRIPTION.md
odoo/addons/tms_expense/readme/INSTALL.md
odoo/addons/tms_expense/readme/MANTAINERS.md
odoo/addons/tms_expense/readme/USAGE.md
odoo/addons/tms_expense/static/description/icon.png
odoo/addons/tms_expense/static/description/icon.svg
odoo/addons/tms_expense/static/description/index.html
odoo/addons/tms_expense/views/hr_employee.xml
odoo/addons/tms_expense/views/hr_expense_views.xml
odoo/addons/tms_expense/views/tms_order.xml
odoo_addon_tms_expense-17.0.1.0.0.2.dist-info/METADATA
odoo_addon_tms_expense-17.0.1.0.0.2.dist-info/WHEEL
odoo_addon_tms_expense-17.0.1.0.0.2.dist-info/top_level.txt
odoo_addon_tms_expense-17.0.1.0.0.2.dist-info/RECORD
